apiminio/__init__.py
apiminio/main.py
apiminio-0.3.6.dist-info/METADATA
apiminio-0.3.6.dist-info/WHEEL
apiminio-0.3.6.dist-info/licenses/LICENSE
apiminio-0.3.6.dist-info/RECORD
