Metadata-Version: 2.4
Name: apiminio
Version: 0.3.6
Summary: apiminio is a Python package that provides a ready-to-use REST API for interacting with MinIO S3 storage, built with FastAPI and the MinIO Python client. It enables seamless file uploads, downloads, and bucket management via HTTP interface ideal for integrating MinIO S3 into your applications with minimal setup.
Project-URL: Homepage, https://raederan.github.io/apiminio/
Project-URL: Repository, https://github.com/raederan/apiminio
Project-URL: Documentation, https://docs.apimin.io
Author-email: Andreas Räder <andreas-raeder@gmx.de>
License-File: LICENSE
Keywords: python
Classifier: Intended Audience :: Developers
Classifier: Programming Language :: Python
Classifier: Programming Language :: Python :: 3
Classifier: Programming Language :: Python :: 3.10
Classifier: Programming Language :: Python :: 3.11
Classifier: Programming Language :: Python :: 3.12
Classifier: Programming Language :: Python :: 3.13
Classifier: Topic :: Software Development :: Libraries :: Python Modules
Requires-Python: <4.0,>=3.10
Requires-Dist: fastapi-mcp>=0.4.0
Requires-Dist: fastapi[standard]>=0.116.1
Requires-Dist: minio>=7.2.16
Requires-Dist: param>=2.2.1
Requires-Dist: pydantic>=2.11.7
